prettyfmt/__init__.py
prettyfmt/plurals.py
prettyfmt/prettyfmt.py
prettyfmt/py.typed
prettyfmt-0.4.1.dist-info/METADATA
prettyfmt-0.4.1.dist-info/WHEEL
prettyfmt-0.4.1.dist-info/licenses/LICENSE
prettyfmt-0.4.1.dist-info/RECORD
