Metadata-Version: 2.4
Name: prettyfmt
Version: 0.4.1
Summary: A tiny library to make your outputs more beautiful
Project-URL: Repository, https://github.com/jlevy/prettyfmt
Author-email: Joshua Levy <joshua@cal.berkeley.edu>
License-Expression: MIT
License-File: LICENSE
Classifier: Development Status :: 4 - Beta
Classifier: Intended Audience :: Developers
Classifier: Operating System :: OS Independent
Classifier: Programming Language :: Python
Classifier: Programming Language :: Python :: 3
Classifier: Programming Language :: Python :: 3.10
Classifier: Programming Language :: Python :: 3.11
Classifier: Programming Language :: Python :: 3.12
Classifier: Programming Language :: Python :: 3.13
Classifier: Typing :: Typed
Requires-Python: <4.0,>=3.10
Requires-Dist: humanize>=4.11.0
Requires-Dist: pluralizer>=1.2.0
Requires-Dist: strif>=3.0.1
Requires-Dist: text-unidecode>=1.3
